<?xml version="1.0" encoding="UTF-8" ?>
<!DOCTYPE mapper  PUBLIC "-//mybatis.org//DTD Mapper 3.0//EN"  "http://mybatis.org/dtd/mybatis-3-mapper.dtd">
<mapper namespace="kh.st.boot.dao.AdminApprovalDAO">

	<select id="SelectAll" resultType="AdmApprovalVO">
		SELECT * FROM
		member_approve
		JOIN member 
		USING(mb_no)
	</select>

	<select id="selectCountList" resultType="int"> SELECT COUNT(*) FROM
		member_approve
	</select>

	<update id="nyUPDATE">
		UPDATE member_approve
		SET mp_yn = #{mp_yn},
		mp_app_date = NOW()
		WHERE mb_no = #{mb_no}
	</update>

	<insert id="newsInsert">
		INSERT INTO news_member (mb_no, mb_news)
		VALUES
		(#{mb_no}, #{mp_company})
	</insert>

	<insert id="stockInsert">
		INSERT INTO stock_member (mb_no, mb_stock)
		VALUES
		(#{mb_no}, #{mp_company})
	</insert>

	<select id="searchApproval" resultType="AdmApprovalVO">
		SELECT * FROM
		member_approve
		JOIN member USING(mb_no)
		WHERE mp_company LIKE CONCAT('%', #{mp_company}, '%')
		LIMIT #{pageStart}, #{perPageNum}
	</select>
	<select id="selectTotalCount" resultType="int"> SELECT COUNT(*) FROM
		member_approve
		WHERE mp_company LIKE CONCAT('%', #{mp_company}, '%')
	</select>

	<update id="stockLvUp">
		UPDATE member
		SET mb_level = 8
		WHERE mb_no = #{mb_no}
	</update>



	<update id="newsLvUp">
		UPDATE member
		SET mb_level = 7
		WHERE mb_no = #{mb_no}
	</update>


	<update id="memberLvDown">
		UPDATE member
		SET mb_level = 1
		WHERE mb_no = #{mb_no}
	</update>


	<delete id="newsDelete">
		DELETE FROM news_member
		WHERE mb_no = #{mb_no}
	</delete>

	<delete id="stockDelete">
		DELETE FROM stock_member
		WHERE mb_no = #{mb_no}
	</delete>

	<select id="ynSearch" resultType="String">
	 	SELECT mp_yn 
   		FROM member_approve
    	WHERE mb_no = #{mb_no}
	</select>


</mapper>
